am_red_channel/__init__.py
am_red_channel/_consts.py
am_red_channel/am.py
am_red_channel-2.1.2.dist-info/LICENSE
am_red_channel-2.1.2.dist-info/METADATA
am_red_channel-2.1.2.dist-info/WHEEL
am_red_channel-2.1.2.dist-info/top_level.txt
am_red_channel-2.1.2.dist-info/RECORD
