Metadata-Version: 2.1
Name: am-red-channel
Version: 2.1.2
Summary: Making connection between bython and Node-RED
Home-page: UNKNOWN
Author: Amr Mostafa (Amr_MAM)
Author-email: <amr.mostafa.abbas@gmail.com>
License: UNKNOWN
Keywords: python,video,stream,video stream,camera stream,sockets,Node-RED
Platform: UNKNOWN
Classifier: Development Status :: 1 - Planning
Classifier: Intended Audience :: Developers
Classifier: Programming Language :: Python :: 3
Classifier: Operating System :: Unix
Classifier: Operating System :: MacOS :: MacOS X
Classifier: Operating System :: Microsoft :: Windows
Requires-Dist: requests
